Workbook

Sheet Data_Entry
B2: RAW DATA — Extracted Figures from Audited Annual Reports (Group Level)
C4: GUARANTY TRUST HOLDING COMPANY (GTCO) | I4: ZENITH BANK PLC
B5: METRIC | C5: 2021 | D5: 2022 | E5: 2023 | F5: 2024 | G5: 2025 | I5: 2021 | J5: 2022 | K5: 2023 | L5: 2024 | M5: 2025 | O5: WHERE TO FIND IT
B6: INCOME STATEMENT (₦ Billions)
B7: Gross Earnings / Total Revenue | C7: 447.81 | D7: 539.24 | E7: 1186.47 | F7: 2148.34 | G7: 2150.37 | I7: 765.56 | J7: 945.55 | K7: 2131.75 | L7: 3970.96 | M7: 4192 | O7: Highlights / Directors’ Report – Operating Results
B8: Net Interest Income | C8: 220.61 | D8: 259.3 | E8: 436.7 | F8: 1058.59 | G8: 1260.59 | I8: 320.8 | J8: 366.63 | K8: 736.18 | L8: 1728.9 | M8: 2639.53 | O8: Highlights / Income Statement
B9: Non-Interest Income (Fees & Commissions) | C9: 74.12 | D9: 90.61 | E9: 124.16 | F9: 221.23 | G9: 278.51 | I9: 132.88 | J9: 157.22 | K9: 177.52 | L9: 356.34 | M9: 404.95 | O9: Notes to FS – Fee & Commission Income
B10: Operating Expenses (OPEX) | C10: 162.27 | D10: 197.9 | E10: 250.42 | F10: 403.03 | G10: 475.37 | I10: 289.53 | J10: 339.69 | K10: 449.47 | L10: 843.35 | M10: 1039.5 | O10: Highlights / Income Statement
B11: Profit Before Tax (PBT) | C11: 221.5 | D11: 214.15 | E11: 609.31 | F11: 1266.25 | G11: 1231.08 | I11: 280.37 | J11: 284.65 | K11: 795.96 | L11: 1326.85 | M11: 1263.37 | O11: Highlights / Directors’ Report
B12: Profit After Tax (PAT) | C12: 174.84 | D12: 169.17 | E12: 539.65 | F12: 1017.8 | G12: 865.75 | I12: 244.56 | J12: 223.91 | K12: 676.91 | L12: 1032.9 | M12: 1040.55 | O12: Highlights / Directors’ Report
B13: Earnings Per Share — EPS (₦) | C13: 6.14 | D13: 5.95 | E13: 19.07 | F13: 35.44 | G13: 25.43 | I13: 7.78 | J13: 7.14 | K13: 21.55 | L13: 32.87 | M13: 25.32 | O13: Highlights / Notes – Earnings per Share
B14: Dividend Per Share — DPS (₦) | C14: 3 | D14: 3.1 | E14: 3.2 | F14: 8.03 | G14: 12.76 | I14: 3.1 | J14: 3.2 | K14: 4 | L14: 5 | M14: 10 | O14: Directors’ Report / Notice of AGM
B15: → PBT Margin % | C15: =IFERROR(C11/C7*100,"—") -> 49.462942 | D15: =IFERROR(D11/D7*100,"—") -> 39.7133 | E15: =IFERROR(E11/E7*100,"—") -> 51.354859 | F15: =IFERROR(F11/F7*100,"—") -> 58.940857 | G15: =IFERROR(G11/G7*100,"—") -> 57.249683 | I15: =IFERROR(I11/I7*100,"—") -> 36.622864 | J15: =IFERROR(J11/J7*100,"—") -> 30.104172 | K15: =IFERROR(K11/K7*100,"—") -> 37.338337 | L15: =IFERROR(L11/L7*100,"—") -> 33.413834 | M15: =IFERROR(M11/M7*100,"—") -> 30.137643 | O15: Calculated (PBT ÷ Gross Earnings)
B16: → PAT Margin % | C16: =IFERROR(C12/C7*100,"—") -> 39.043344 | D16: =IFERROR(D12/D7*100,"—") -> 31.371931 | E16: =IFERROR(E12/E7*100,"—") -> 45.483662 | F16: =IFERROR(F12/F7*100,"—") -> 47.376114 | G16: =IFERROR(G12/G7*100,"—") -> 40.260513 | I16: =IFERROR(I12/I7*100,"—") -> 31.945243 | J16: =IFERROR(J12/J7*100,"—") -> 23.680398 | K16: =IFERROR(K12/K7*100,"—") -> 31.753723 | L16: =IFERROR(L12/L7*100,"—") -> 26.011342 | M16: =IFERROR(M12/M7*100,"—") -> 24.822281 | O16: Calculated (PAT ÷ Gross Earnings)
B17: → YoY PAT Growth % | C17: — | D17: =IFERROR((D12-C12)/C12*100,"—") -> -3.242965 | E17: =IFERROR((E12-D12)/D12*100,"—") -> 218.99864 | F17: =IFERROR((F12-E12)/E12*100,"—") -> 88.603725 | G17: =IFERROR((G12-F12)/F12*100,"—") -> -14.939084 | I17: — | J17: =IFERROR((J12-I12)/I12*100,"—") -> -8.4437357 | K17: =IFERROR((K12-J12)/J12*100,"—") -> 202.31343 | L17: =IFERROR((L12-K12)/K12*100,"—") -> 52.590448 | M17: =IFERROR((M12-L12)/L12*100,"—") -> 0.74063317 | O17: Calculated
B18: BALANCE SHEET (₦ Billions)
B19: Total Assets | C19: 5436.03 | D19: 6446.46 | E19: 9691.25 | F19: 14795.71 | G19: 17761.15 | I19: 9447.84 | J19: 12285.63 | K19: 20368.46 | L19: 29957.53 | M19: 31458.05 | O19: Statement of Financial Position
B20: Customer Deposits / Total Deposits | C20: 4012.31 | D20: 4485.11 | E20: 7410.83 | F20: 10013.02 | G20: 12874.04 | I20: 6472.05 | J20: 8975.65 | K20: 15167.74 | L20: 21959.37 | M20: 24329.96 | O20: Statement of Financial Position / Highlights
B21: Loans & Advances to Customers (Net) | C21: 1802.59 | D21: 1885.8 | E21: 2480.18 | F21: 2795.66 | G21: 3132.22 | I21: 3355.73 | J21: 4013.71 | K21: 6556.47 | L21: 9965.36 | M21: 10448.95 | O21: Statement of Financial Position
B22: Shareholders' Equity / Total Equity | C22: 883.23 | D22: 931.15 | E22: 1477.13 | F22: 2712.02 | G22: 3411.38 | I22: 1279.66 | J22: 1378.94 | K22: 2323.38 | L22: 4029.27 | M22: 4924.21 | O22: Statement of Financial Position / Highlights
B23: → Loan-to-Deposit Ratio % | C23: =IFERROR((C21/C20)*100,"—") -> 44.926489 | D23: =IFERROR((D21/D20)*100,"—") -> 42.045792 | E23: =IFERROR((E21/E20)*100,"—") -> 33.466967 | F23: =IFERROR((F21/F20)*100,"—") -> 27.920248 | G23: =IFERROR((G21/G20)*100,"—") -> 24.329736 | I23: =IFERROR(I21/I20*100,"—") -> 51.849569 | J23: =IFERROR(J21/J20*100,"—") -> 44.717764 | K23: =IFERROR(K21/K20*100,"—") -> 43.226413 | L23: =IFERROR(L21/L20*100,"—") -> 45.380901 | M23: =IFERROR(M21/M20*100,"—") -> 42.946844 | O23: Calculated (Net Loans ÷ Deposits)
B24: → Equity-to-Asset Ratio % | C24: =IFERROR((C22/C19)*100,"—") -> 16.247703 | D24: =IFERROR((D22/D19)*100,"—") -> 14.444362 | E24: =IFERROR((E22/E19)*100,"—") -> 15.241893 | F24: =IFERROR((F22/F19)*100,"—") -> 18.329773 | G24: =IFERROR((G22/G19)*100,"—") -> 19.206977 | I24: =IFERROR(I22/I19*100,"—") -> 13.544472 | J24: =IFERROR(J22/J19*100,"—") -> 11.224007 | K24: =IFERROR(K22/K19*100,"—") -> 11.406753 | L24: =IFERROR(L22/L19*100,"—") -> 13.449941 | M24: =IFERROR(M22/M19*100,"—") -> 15.653259 | O24: Calculated (Equity ÷ Total Assets)
B25: KEY RATIOS
B26: Return on Equity — ROE % | C26: 20.6 | D26: 18.65 | E26: 44.82 | F26: 48.59 | G26: 40.21 | I26: 20.4 | J26: 16.8 | K26: 36.6 | L26: 32.5 | M26: 23.2 | O26: Key Ratios / Highlights (ROAE)
B27: Return on Assets — ROA % | C27: 3.37 | D27: 2.85 | E27: 6.69 | F27: 8.31 | G27: 7.56 | I27: 2.7 | J27: 2.1 | K27: 4.1 | L27: 4.1 | M27: 3.4 | O27: Key Ratios / Highlights (ROAA)
B28: Capital Adequacy Ratio — CAR % | C28: 23.83 | D28: 24.08 | E28: 21.94 | F28: 39.31 | G28: 43.82 | I28: 21 | J28: 19.8 | K28: 21.7 | L28: 25.6 | M28: 25.3 | O28: Key Ratios / Notes – Capital Adequacy
B29: Cost-to-Income Ratio % | D29: 48.03 | E29: 29.13 | F29: 24.14 | G29: 27.86 | I29: 50.8 | J29: 54.4 | K29: 36.1 | L29: 38.9 | M29: 45.2 | O29: Key Ratios / Highlights
B30: Net Loan Loss Ratio % | D30: 0.62 | E30: 4.49 | F30: 4.94 | G30: 2.16 | I30: 4.19 | J30: 4.3 | K30: 4.82 | L30: 3.48 | M30: 3.8 | O30: Key Ratios / Highlights (NPL or Net Loan Loss)

Sheet Dashboard
B2: GTBank vs Zenith Bank — Financial Dashboard
B3: 5-Year Comparison (2021–2025) | Built by Emmanuel Nwankwo
B5: 2025 SNAPSHOT | G5: KEY INSIGHTS
B6: METRIC | C6: GTCO | D6: ZENITH | E6: WINNER | G6: • GTCO maintains superior profitability (higher ROE and better Cost-to-Income)
B7: Gross Earnings (₦bn) | C7: =Data_Entry!G7 -> 2150.37 | D7: =Data_Entry!M7 -> 4192 | E7: =IFERROR(IF(C7>D7,"GTCO ✓",IF(D7>C7,"ZENITH ✓","TIE")),"—") -> ZENITH ✓ | G7: • Zenith leads significantly in scale (Gross Earnings and Total Assets)
B8: Profit Before Tax (₦bn) | C8: =Data_Entry!G11 -> 1231.08 | D8: =Data_Entry!M11 -> 1263.37 | E8: =IFERROR(IF(C8>D8,"GTCO ✓",IF(D8>C8,"ZENITH ✓","TIE")),"—") -> ZENITH ✓ | G8: • Both banks strengthened capital positions, with GTCO showing the strongest CAR
B9: Profit After Tax (₦bn) | C9: =Data_Entry!G12 -> 865.75 | D9: =Data_Entry!M12 -> 1040.55 | E9: =IFERROR(IF(C9>D9,"GTCO ✓",IF(D9>C9,"ZENITH ✓","TIE")),"—") -> ZENITH ✓ | G9: • Asset quality improved for both, with GTCO posting lower Net Loan Loss Ratio in 2025
B10: Total Assets (₦bn) | C10: =Data_Entry!G19 -> 17761.15 | D10: =Data_Entry!M19 -> 31458.05 | E10: =IFERROR(IF(C10>D10,"GTCO ✓",IF(D10>C10,"ZENITH ✓","TIE")),"—") -> ZENITH ✓ | G10: • Zenith delivered stronger absolute profit growth over the 5-year period
B11: Customer Deposits (₦bn) | C11: =Data_Entry!G20 -> 12874.04 | D11: =Data_Entry!M20 -> 24329.96 | E11: =IFERROR(IF(C11>D11,"GTCO ✓",IF(D11>C11,"ZENITH ✓","TIE")),"—") -> ZENITH ✓
B12: ROE (%) | C12: =Data_Entry!G26 -> 40.21 | D12: =Data_Entry!M26 -> 23.2 | E12: =IFERROR(IF(C12>D12,"GTCO ✓",IF(D12>C12,"ZENITH ✓","TIE")),"—") -> GTCO ✓
B13: ROA (%) | C13: =Data_Entry!G27 -> 7.56 | D13: =Data_Entry!M27 -> 3.4 | E13: =IFERROR(IF(C13>D13,"GTCO ✓",IF(D13>C13,"ZENITH ✓","TIE")),"—") -> GTCO ✓
B14: Capital Adequacy (CAR %) | C14: =Data_Entry!G28 -> 43.82 | D14: =Data_Entry!M28 -> 25.3 | E14: =IFERROR(IF(C14>D14,"GTCO ✓",IF(D14>C14,"ZENITH ✓","TIE")),"—") -> GTCO ✓ | I14: vs
B15: Cost-to-Income (%) | C15: =Data_Entry!G29 -> 27.86 | D15: =Data_Entry!M29 -> 45.2 | E15: =IFERROR(IF(C15<D15,"GTCO ✓",IF(D15<C15,"ZENITH ✓","TIE")),"—") -> GTCO ✓
B16: Net Loan Loss Ratio % | C16: =Data_Entry!G30 -> 2.16 | D16: =Data_Entry!M30 -> 3.8 | E16: =IFERROR(IF(C16<D16,"GTCO ✓",IF(D16<C16,"ZENITH ✓","TIE")),"—") -> GTCO ✓
B17: EPS (₦) | C17: =Data_Entry!G13 -> 25.43 | D17: =Data_Entry!M13 -> 25.32 | E17: =IFERROR(IF(C17>D17,"GTCO ✓",IF(D17>C17,"ZENITH ✓","TIE")),"—") -> GTCO ✓
B18: METRICS WON (out of 11): | C18: =COUNTIF(E7:E17,"GTCO ✓") -> 6 | D18: =COUNTIF(E7:E17,"ZENITH ✓") -> 5 | E18: =IF(C18>D18,"GTCO LEADS",IF(D18>C18,"ZENITH LEADS","TIED")) -> GTCO LEADS
